doze_detect.py
doze_detect-0.0.1.dist-info/METADATA
doze_detect-0.0.1.dist-info/WHEEL
doze_detect-0.0.1.dist-info/entry_points.txt
doze_detect-0.0.1.dist-info/top_level.txt
doze_detect-0.0.1.dist-info/RECORD
