Metadata-Version: 2.1
Name: doze_detect
Version: 0.0.1
Summary: Doze detection application
Home-page: https://github.com/MinhChaosBoDoiQua/Doze-Detection
Author: Nguyen Tien Minh
Author-email: tienminh2312@gmail.com
License: UNKNOWN
Project-URL: Bug Tracker, https://github.com/MinhChaosBoDoiQua/Doze-Detection
Platform: UNKNOWN
Classifier: Programming Language :: Python :: 3
Classifier: License :: OSI Approved :: MIT License
Classifier: Operating System :: OS Independent
Requires-Python: >=3.7
